bpg400/__init__.py
bpg400/bpg400.py
bpg400/bpg400cli.py
pybpg400_tspspi-0.0.2.dist-info/LICENSE.md
pybpg400_tspspi-0.0.2.dist-info/METADATA
pybpg400_tspspi-0.0.2.dist-info/WHEEL
pybpg400_tspspi-0.0.2.dist-info/entry_points.txt
pybpg400_tspspi-0.0.2.dist-info/top_level.txt
pybpg400_tspspi-0.0.2.dist-info/RECORD
