Metadata-Version: 2.1
Name: pybpg400-tspspi
Version: 0.0.2
Summary: Unofficial library to control and read the BPG400 pressure gauge via RS232C interface
Home-page: https://github.com/tspspi/pybpg400
Author: Thomas Spielauer
Author-email: pypipackages01@tspi.at
Classifier: Programming Language :: Python :: 3
Classifier: License :: OSI Approved :: BSD License
Classifier: Operating System :: OS Independent
Requires-Python: >=3.6
License-File: LICENSE.md
Requires-Dist: pylabdevs-tspspi (>=0.0.8)
Requires-Dist: pyserial (>=3.5)
